pyvis/__init__.py
pyvis/_version.py
pyvis/edge.py
pyvis/network.py
pyvis/node.py
pyvis/options.py
pyvis/physics.py
pyvis/utils.py
pyvis/templates/animation_template.html
pyvis/templates/template.html
pyvis/templates/lib/bindings/utils.js
pyvis/templates/lib/tom-select/tom-select.complete.min.js
pyvis/templates/lib/tom-select/tom-select.css
pyvis/templates/lib/vis-9.0.4/vis-network.css
pyvis/templates/lib/vis-9.0.4/vis-network.min.js
pyvis/templates/lib/vis-9.1.2/vis-network.css
pyvis/templates/lib/vis-9.1.2/vis-network.min.js
pyvis/tests/__init__.py
pyvis/tests/test_graph.py
pyvis/tests/test_html.py
pyvis/tests/test_me.py
fattaholmanan_pyvis-1.0.8.dist-info/LICENSE_BSD.txt
fattaholmanan_pyvis-1.0.8.dist-info/METADATA
fattaholmanan_pyvis-1.0.8.dist-info/WHEEL
fattaholmanan_pyvis-1.0.8.dist-info/top_level.txt
fattaholmanan_pyvis-1.0.8.dist-info/RECORD
