Metadata-Version: 2.2
Name: fattaholmanan-pyvis
Version: 1.0.8
Summary: A Python network graph visualization library
Home-page: https://github.com/fattaholmanan/pyvis
Author: Ali Fattaholmanan
Author-email: alii.fattah@gmail.com
License: BSD
Requires-Python: >3.6
License-File: LICENSE_BSD.txt
Requires-Dist: jinja2>=2.9.6
Requires-Dist: networkx>=1.11
Requires-Dist: ipython>=5.3.0
Requires-Dist: jsonpickle>=1.4.1
Dynamic: author
Dynamic: author-email
Dynamic: description
Dynamic: description-content-type
Dynamic: home-page
Dynamic: license
Dynamic: requires-dist
Dynamic: requires-python
Dynamic: summary
